nodeview/__init__.py
nodeview/nodeview.py
nodeview-0.1.0.dev0.data/data/nodeview/config.toml
nodeview-0.1.0.dev0.dist-info/LICENSE
nodeview-0.1.0.dev0.dist-info/METADATA
nodeview-0.1.0.dev0.dist-info/WHEEL
nodeview-0.1.0.dev0.dist-info/entry_points.txt
nodeview-0.1.0.dev0.dist-info/top_level.txt
nodeview-0.1.0.dev0.dist-info/RECORD
